logux/__init__.py
logux/apps.py
logux/core.py
logux/dispatchers.py
logux/exceptions.py
logux/settings.py
logux/throttling.py
logux/urls.py
logux/utils.py
logux/views.py
logux_django-2.0.dist-info/LICENSE
logux_django-2.0.dist-info/METADATA
logux_django-2.0.dist-info/WHEEL
logux_django-2.0.dist-info/top_level.txt
logux_django-2.0.dist-info/RECORD
