Metadata-Version: 2.1
Name: logux-django
Version: 2.0
Summary: Django Logux integration engine https://logux.io/
Home-page: https://github.com/logux/django/
Author: Vadim Iskuchekov @egregors
Author-email: egregors@pm.me
License: MIT
Platform: UNKNOWN
Classifier: Development Status :: 4 - Beta
Classifier: Environment :: Web Environment
Classifier: Intended Audience :: Developers
Classifier: License :: OSI Approved :: MIT License
Classifier: Operating System :: OS Independent
Classifier: Programming Language :: Python
Classifier: Programming Language :: Python :: 3.7
Requires-Python: >=3.7
Requires-Dist: django (<4,>=2.2)
Requires-Dist: requests (<3,>=2.22.0)
Requires-Dist: semantic-version (==2.8.5)
